simplelogger/__init__.py
simplelogger/__main__.py
simplelogger/info.py
simplelogger/logger.py
simplelogger_python-0.1.10.dist-info/LICENSE
simplelogger_python-0.1.10.dist-info/METADATA
simplelogger_python-0.1.10.dist-info/WHEEL
simplelogger_python-0.1.10.dist-info/top_level.txt
simplelogger_python-0.1.10.dist-info/RECORD
