Metadata-Version: 2.1
Name: simplelogger-python
Version: 0.1.10
Summary: A simple logger I made for some projects a year ago.
Home-page: https://github.com/Chris1320/SimpleLogger-python
Author: Chris1320
Author-email: chris1320is@protonmail.com
License: MIT
Platform: UNKNOWN
Classifier: Development Status :: 3 - Alpha
Classifier: License :: OSI Approved :: MIT License
Classifier: Programming Language :: Python :: 3.7
Classifier: Topic :: System :: Logging
License-File: LICENSE
Provides-Extra: colors
Requires-Dist: colorama ; extra == 'colors'
